{
  "name": "AS29844",
  "total_nodes": 1,
  "reachable_nodes": 1,
  "unreachable_nodes": 0,
  "tor_nodes": 0,
  "ipv4_nodes": 1,
  "ipv6_nodes": 0,
  "avg_latency_ms": 0.0,
  "latest_height": 951401,
  "top_agent": "/Satoshi:31.0.0/",
  "top_asn": "AS29844",
  "top_organization": "Sena Wave LLC",
  "top_port": "8333",
  "asn": "AS29844",
  "nodes": [
    {
      "rank": 170,
      "address": "162.218.223.25:8333",
      "host": "162.218.223.25",
      "port": 8333,
      "network": "ipv4",
      "reachable": true,
      "protocol": 70016,
      "agent": "/Satoshi:31.0.0/",
      "connected_since": 1779965258,
      "services": 3145,
      "height": 951401,
      "hostname": null,
      "city": "Salt Lake City (Downtown)",
      "country": "US",
      "latitude": 40.7687,
      "longitude": -111.886,
      "timezone": null,
      "asn": "AS29844",
      "organization": "Sena Wave LLC",
      "provider": null,
      "county": null,
      "zip": null,
      "w3w": null,
      "geohash": null,
      "asn_location": null,
      "latency_ms": 0.0,
      "uptime_human": "10h",
      "uptime_seconds": null,
      "peer_index": 238.69,
      "tor": false,
      "success_count": 131,
      "failure_count": 4,
      "first_seen": "2026-05-28T00:02:17Z",
      "last_seen": "2026-05-28T10:46:37Z"
    }
  ]
}
