{"schema":"zzx-bitnodes-map-county-layers-v1","generated_at":"2026-06-05T04:18:03+00:00","layers":[{"id":"county:US:US:US:UNKNOWN:US:US:UNKNOWN:Unknown","label":"US:US:UNKNOWN:Unknown","kind":"county-filter","enabled":true,"visible":false,"color":"#8c927e","point_count":542,"filter":{"type":"county","key":"map_county","value":"US:US:US:UNKNOWN:US:US:UNKNOWN:Unknown"}},{"id":"county:DE:DE:DE:UNKNOWN:DE:DE:UNKNOWN:Unknown","label":"DE:DE:UNKNOWN:Unknown","kind":"county-filter","enabled":true,"visible":false,"color":"#8c927e","point_count":355,"filter":{"type":"county","key":"map_county","value":"DE:DE:DE:UNKNOWN:DE:DE:UNKNOWN:Unknown"}},{"id":"county:NL:NL:NL:UNKNOWN:NL:NL:UNKNOWN:Unknown","label":"NL:NL:UNKNOWN:Unknown","kind":"county-filter","enabled":true,"visible":false,"color":"#8c927e","point_count":96,"filter":{"type":"county","key":"map_county","value":"NL:NL:NL:UNKNOWN:NL:NL:UNKNOWN:Unknown"}},{"id":"county:FR:FR:FR:UNKNOWN:FR:FR:UNKNOWN:Unknown","label":"FR:FR:UNKNOWN:Unknown","kind":"county-filter","enabled":true,"visible":false,"color":"#8c927e","point_count":93,"filter":{"type":"county","key":"map_county","value":"FR:FR:FR:UNKNOWN:FR:FR:UNKNOWN:Unknown"}},{"id":"county:CA:CA:CA:UNKNOWN:CA:CA:UNKNOWN:Unknown","label":"CA:CA:UNKNOWN:Unknown","kind":"county-filter","enabled":true,"visible":false,"color":"#8c927e","point_count":88,"filter":{"type":"county","key":"map_county","value":"CA:CA:CA:UNKNOWN:CA:CA:UNKNOWN:Unknown"}},{"id":"county:GB:GB:GB:UNKNOWN:GB:GB:UNKNOWN:Unknown","label":"GB:GB:UNKNOWN:Unknown","kind":"county-filter","enabled":true,"visible":false,"color":"#8c927e","point_count":69,"filter":{"type":"county","key":"map_county","value":"GB:GB:GB:UNKNOWN:GB:GB:UNKNOWN:Unknown"}},{"id":"county:SG:SG:SG:UNKNOWN:SG:SG:UNKNOWN:Unknown","label":"SG:SG:UNKNOWN:Unknown","kind":"county-filter","enabled":true,"visible":false,"color":"#8c927e","point_count":39,"filter":{"type":"county","key":"map_county","value":"SG:SG:SG:UNKNOWN:SG:SG:UNKNOWN:Unknown"}},{"id":"county:AU:AU:AU:UNKNOWN:AU:AU:UNKNOWN:Unknown","label":"AU:AU:UNKNOWN:Unknown","kind":"county-filter","enabled":true,"visible":false,"color":"#8c927e","point_count":31,"filter":{"type":"county","key":"map_county","value":"AU:AU:AU:UNKNOWN:AU:AU:UNKNOWN:Unknown"}},{"id":"county:JP:JP:JP:UNKNOWN:JP:JP:UNKNOWN:Unknown","label":"JP:JP:UNKNOWN:Unknown","kind":"county-filter","enabled":true,"visible":false,"color":"#8c927e","point_count":28,"filter":{"type":"county","key":"map_county","value":"JP:JP:JP:UNKNOWN:JP:JP:UNKNOWN:Unknown"}},{"id":"county:CH:CH:CH:UNKNOWN:CH:CH:UNKNOWN:Unknown","label":"CH:CH:UNKNOWN:Unknown","kind":"county-filter","enabled":true,"visible":false,"color":"#8c927e","point_count":19,"filter":{"type":"county","key":"map_county","value":"CH:CH:CH:UNKNOWN:CH:CH:UNKNOWN:Unknown"}},{"id":"county:RU:RU:RU:UNKNOWN:RU:RU:UNKNOWN:Unknown","label":"RU:RU:UNKNOWN:Unknown","kind":"county-filter","enabled":true,"visible":false,"color":"#8c927e","point_count":17,"filter":{"type":"county","key":"map_county","value":"RU:RU:RU:UNKNOWN:RU:RU:UNKNOWN:Unknown"}},{"id":"county:FI:FI:FI:UNKNOWN:FI:FI:UNKNOWN:Unknown","label":"FI:FI:UNKNOWN:Unknown","kind":"county-filter","enabled":true,"visible":false,"color":"#8c927e","point_count":16,"filter":{"type":"county","key":"map_county","value":"FI:FI:FI:UNKNOWN:FI:FI:UNKNOWN:Unknown"}},{"id":"county:ES:ES:ES:UNKNOWN:ES:ES:UNKNOWN:Unknown","label":"ES:ES:UNKNOWN:Unknown","kind":"county-filter","enabled":true,"visible":false,"color":"#8c927e","point_count":13,"filter":{"type":"county","key":"map_county","value":"ES:ES:ES:UNKNOWN:ES:ES:UNKNOWN:Unknown"}},{"id":"county:BR:BR:BR:UNKNOWN:BR:BR:UNKNOWN:Unknown","label":"BR:BR:UNKNOWN:Unknown","kind":"county-filter","enabled":true,"visible":false,"color":"#8c927e","point_count":12,"filter":{"type":"county","key":"map_county","value":"BR:BR:BR:UNKNOWN:BR:BR:UNKNOWN:Unknown"}},{"id":"county:SE:SE:SE:UNKNOWN:SE:SE:UNKNOWN:Unknown","label":"SE:SE:UNKNOWN:Unknown","kind":"county-filter","enabled":true,"visible":false,"color":"#8c927e","point_count":11,"filter":{"type":"county","key":"map_county","value":"SE:SE:SE:UNKNOWN:SE:SE:UNKNOWN:Unknown"}},{"id":"county:AT:AT:AT:UNKNOWN:AT:AT:UNKNOWN:Unknown","label":"AT:AT:UNKNOWN:Unknown","kind":"county-filter","enabled":true,"visible":false,"color":"#8c927e","point_count":10,"filter":{"type":"county","key":"map_county","value":"AT:AT:AT:UNKNOWN:AT:AT:UNKNOWN:Unknown"}},{"id":"county:IT:IT:IT:UNKNOWN:IT:IT:UNKNOWN:Unknown","label":"IT:IT:UNKNOWN:Unknown","kind":"county-filter","enabled":true,"visible":false,"color":"#8c927e","point_count":9,"filter":{"type":"county","key":"map_county","value":"IT:IT:IT:UNKNOWN:IT:IT:UNKNOWN:Unknown"}},{"id":"county:CN:CN:CN:UNKNOWN:CN:CN:UNKNOWN:Unknown","label":"CN:CN:UNKNOWN:Unknown","kind":"county-filter","enabled":true,"visible":false,"color":"#8c927e","point_count":7,"filter":{"type":"county","key":"map_county","value":"CN:CN:CN:UNKNOWN:CN:CN:UNKNOWN:Unknown"}},{"id":"county:KR:KR:KR:UNKNOWN:KR:KR:UNKNOWN:Unknown","label":"KR:KR:UNKNOWN:Unknown","kind":"county-filter","enabled":true,"visible":false,"color":"#8c927e","point_count":7,"filter":{"type":"county","key":"map_county","value":"KR:KR:KR:UNKNOWN:KR:KR:UNKNOWN:Unknown"}},{"id":"county:ZA:ZA:ZA:UNKNOWN:ZA:ZA:UNKNOWN:Unknown","label":"ZA:ZA:UNKNOWN:Unknown","kind":"county-filter","enabled":true,"visible":false,"color":"#8c927e","point_count":7,"filter":{"type":"county","key":"map_county","value":"ZA:ZA:ZA:UNKNOWN:ZA:ZA:UNKNOWN:Unknown"}},{"id":"county:PL:PL:PL:UNKNOWN:PL:PL:UNKNOWN:Unknown","label":"PL:PL:UNKNOWN:Unknown","kind":"county-filter","enabled":true,"visible":false,"color":"#8c927e","point_count":6,"filter":{"type":"county","key":"map_county","value":"PL:PL:PL:UNKNOWN:PL:PL:UNKNOWN:Unknown"}},{"id":"county:BE:BE:BE:UNKNOWN:BE:BE:UNKNOWN:Unknown","label":"BE:BE:UNKNOWN:Unknown","kind":"county-filter","enabled":true,"visible":false,"color":"#8c927e","point_count":5,"filter":{"type":"county","key":"map_county","value":"BE:BE:BE:UNKNOWN:BE:BE:UNKNOWN:Unknown"}},{"id":"county:MX:MX:MX:UNKNOWN:MX:MX:UNKNOWN:Unknown","label":"MX:MX:UNKNOWN:Unknown","kind":"county-filter","enabled":true,"visible":false,"color":"#8c927e","point_count":5,"filter":{"type":"county","key":"map_county","value":"MX:MX:MX:UNKNOWN:MX:MX:UNKNOWN:Unknown"}},{"id":"county:NZ:NZ:NZ:UNKNOWN:NZ:NZ:UNKNOWN:Unknown","label":"NZ:NZ:UNKNOWN:Unknown","kind":"county-filter","enabled":true,"visible":false,"color":"#8c927e","point_count":5,"filter":{"type":"county","key":"map_county","value":"NZ:NZ:NZ:UNKNOWN:NZ:NZ:UNKNOWN:Unknown"}},{"id":"county:RO:RO:RO:UNKNOWN:RO:RO:UNKNOWN:Unknown","label":"RO:RO:UNKNOWN:Unknown","kind":"county-filter","enabled":true,"visible":false,"color":"#8c927e","point_count":5,"filter":{"type":"county","key":"map_county","value":"RO:RO:RO:UNKNOWN:RO:RO:UNKNOWN:Unknown"}},{"id":"county:TH:TH:TH:UNKNOWN:TH:TH:UNKNOWN:Unknown","label":"TH:TH:UNKNOWN:Unknown","kind":"county-filter","enabled":true,"visible":false,"color":"#8c927e","point_count":5,"filter":{"type":"county","key":"map_county","value":"TH:TH:TH:UNKNOWN:TH:TH:UNKNOWN:Unknown"}},{"id":"county:CZ:CZ:CZ:UNKNOWN:CZ:CZ:UNKNOWN:Unknown","label":"CZ:CZ:UNKNOWN:Unknown","kind":"county-filter","enabled":true,"visible":false,"color":"#8c927e","point_count":4,"filter":{"type":"county","key":"map_county","value":"CZ:CZ:CZ:UNKNOWN:CZ:CZ:UNKNOWN:Unknown"}},{"id":"county:IE:IE:IE:UNKNOWN:IE:IE:UNKNOWN:Unknown","label":"IE:IE:UNKNOWN:Unknown","kind":"county-filter","enabled":true,"visible":false,"color":"#8c927e","point_count":4,"filter":{"type":"county","key":"map_county","value":"IE:IE:IE:UNKNOWN:IE:IE:UNKNOWN:Unknown"}},{"id":"county:PT:PT:PT:UNKNOWN:PT:PT:UNKNOWN:Unknown","label":"PT:PT:UNKNOWN:Unknown","kind":"county-filter","enabled":true,"visible":false,"color":"#8c927e","point_count":4,"filter":{"type":"county","key":"map_county","value":"PT:PT:PT:UNKNOWN:PT:PT:UNKNOWN:Unknown"}},{"id":"county:AE:AE:AE:UNKNOWN:AE:AE:UNKNOWN:Unknown","label":"AE:AE:UNKNOWN:Unknown","kind":"county-filter","enabled":true,"visible":false,"color":"#8c927e","point_count":3,"filter":{"type":"county","key":"map_county","value":"AE:AE:AE:UNKNOWN:AE:AE:UNKNOWN:Unknown"}},{"id":"county:AR:AR:AR:UNKNOWN:AR:AR:UNKNOWN:Unknown","label":"AR:AR:UNKNOWN:Unknown","kind":"county-filter","enabled":true,"visible":false,"color":"#8c927e","point_count":3,"filter":{"type":"county","key":"map_county","value":"AR:AR:AR:UNKNOWN:AR:AR:UNKNOWN:Unknown"}},{"id":"county:HK:HK:HK:UNKNOWN:HK:HK:UNKNOWN:Unknown","label":"HK:HK:UNKNOWN:Unknown","kind":"county-filter","enabled":true,"visible":false,"color":"#8c927e","point_count":3,"filter":{"type":"county","key":"map_county","value":"HK:HK:HK:UNKNOWN:HK:HK:UNKNOWN:Unknown"}},{"id":"county:HU:HU:HU:UNKNOWN:HU:HU:UNKNOWN:Unknown","label":"HU:HU:UNKNOWN:Unknown","kind":"county-filter","enabled":true,"visible":false,"color":"#8c927e","point_count":3,"filter":{"type":"county","key":"map_county","value":"HU:HU:HU:UNKNOWN:HU:HU:UNKNOWN:Unknown"}},{"id":"county:NO:NO:NO:UNKNOWN:NO:NO:UNKNOWN:Unknown","label":"NO:NO:UNKNOWN:Unknown","kind":"county-filter","enabled":true,"visible":false,"color":"#8c927e","point_count":3,"filter":{"type":"county","key":"map_county","value":"NO:NO:NO:UNKNOWN:NO:NO:UNKNOWN:Unknown"}},{"id":"county:SI:SI:SI:UNKNOWN:SI:SI:UNKNOWN:Unknown","label":"SI:SI:UNKNOWN:Unknown","kind":"county-filter","enabled":true,"visible":false,"color":"#8c927e","point_count":3,"filter":{"type":"county","key":"map_county","value":"SI:SI:SI:UNKNOWN:SI:SI:UNKNOWN:Unknown"}},{"id":"county:SK:SK:SK:UNKNOWN:SK:SK:UNKNOWN:Unknown","label":"SK:SK:UNKNOWN:Unknown","kind":"county-filter","enabled":true,"visible":false,"color":"#8c927e","point_count":3,"filter":{"type":"county","key":"map_county","value":"SK:SK:SK:UNKNOWN:SK:SK:UNKNOWN:Unknown"}},{"id":"county:TW:TW:TW:UNKNOWN:TW:TW:UNKNOWN:Unknown","label":"TW:TW:UNKNOWN:Unknown","kind":"county-filter","enabled":true,"visible":false,"color":"#8c927e","point_count":3,"filter":{"type":"county","key":"map_county","value":"TW:TW:TW:UNKNOWN:TW:TW:UNKNOWN:Unknown"}},{"id":"county:BG:BG:BG:UNKNOWN:BG:BG:UNKNOWN:Unknown","label":"BG:BG:UNKNOWN:Unknown","kind":"county-filter","enabled":true,"visible":false,"color":"#8c927e","point_count":2,"filter":{"type":"county","key":"map_county","value":"BG:BG:BG:UNKNOWN:BG:BG:UNKNOWN:Unknown"}},{"id":"county:CO:CO:CO:UNKNOWN:CO:CO:UNKNOWN:Unknown","label":"CO:CO:UNKNOWN:Unknown","kind":"county-filter","enabled":true,"visible":false,"color":"#8c927e","point_count":2,"filter":{"type":"county","key":"map_county","value":"CO:CO:CO:UNKNOWN:CO:CO:UNKNOWN:Unknown"}},{"id":"county:GR:GR:GR:UNKNOWN:GR:GR:UNKNOWN:Unknown","label":"GR:GR:UNKNOWN:Unknown","kind":"county-filter","enabled":true,"visible":false,"color":"#8c927e","point_count":2,"filter":{"type":"county","key":"map_county","value":"GR:GR:GR:UNKNOWN:GR:GR:UNKNOWN:Unknown"}},{"id":"county:IL:IL:IL:UNKNOWN:IL:IL:UNKNOWN:Unknown","label":"IL:IL:UNKNOWN:Unknown","kind":"county-filter","enabled":true,"visible":false,"color":"#8c927e","point_count":2,"filter":{"type":"county","key":"map_county","value":"IL:IL:IL:UNKNOWN:IL:IL:UNKNOWN:Unknown"}},{"id":"county:IN:IN:IN:UNKNOWN:IN:IN:UNKNOWN:Unknown","label":"IN:IN:UNKNOWN:Unknown","kind":"county-filter","enabled":true,"visible":false,"color":"#8c927e","point_count":2,"filter":{"type":"county","key":"map_county","value":"IN:IN:IN:UNKNOWN:IN:IN:UNKNOWN:Unknown"}},{"id":"county:LT:LT:LT:UNKNOWN:LT:LT:UNKNOWN:Unknown","label":"LT:LT:UNKNOWN:Unknown","kind":"county-filter","enabled":true,"visible":false,"color":"#8c927e","point_count":2,"filter":{"type":"county","key":"map_county","value":"LT:LT:LT:UNKNOWN:LT:LT:UNKNOWN:Unknown"}},{"id":"county:MT:MT:MT:UNKNOWN:MT:MT:UNKNOWN:Unknown","label":"MT:MT:UNKNOWN:Unknown","kind":"county-filter","enabled":true,"visible":false,"color":"#8c927e","point_count":2,"filter":{"type":"county","key":"map_county","value":"MT:MT:MT:UNKNOWN:MT:MT:UNKNOWN:Unknown"}},{"id":"county:TR:TR:TR:UNKNOWN:TR:TR:UNKNOWN:Unknown","label":"TR:TR:UNKNOWN:Unknown","kind":"county-filter","enabled":true,"visible":false,"color":"#8c927e","point_count":2,"filter":{"type":"county","key":"map_county","value":"TR:TR:TR:UNKNOWN:TR:TR:UNKNOWN:Unknown"}},{"id":"county:UY:UY:UY:UNKNOWN:UY:UY:UNKNOWN:Unknown","label":"UY:UY:UNKNOWN:Unknown","kind":"county-filter","enabled":true,"visible":false,"color":"#8c927e","point_count":2,"filter":{"type":"county","key":"map_county","value":"UY:UY:UY:UNKNOWN:UY:UY:UNKNOWN:Unknown"}},{"id":"county:BY:BY:BY:UNKNOWN:BY:BY:UNKNOWN:Unknown","label":"BY:BY:UNKNOWN:Unknown","kind":"county-filter","enabled":true,"visible":false,"color":"#8c927e","point_count":1,"filter":{"type":"county","key":"map_county","value":"BY:BY:BY:UNKNOWN:BY:BY:UNKNOWN:Unknown"}},{"id":"county:CL:CL:CL:UNKNOWN:CL:CL:UNKNOWN:Unknown","label":"CL:CL:UNKNOWN:Unknown","kind":"county-filter","enabled":true,"visible":false,"color":"#8c927e","point_count":1,"filter":{"type":"county","key":"map_county","value":"CL:CL:CL:UNKNOWN:CL:CL:UNKNOWN:Unknown"}},{"id":"county:DK:DK:DK:UNKNOWN:DK:DK:UNKNOWN:Unknown","label":"DK:DK:UNKNOWN:Unknown","kind":"county-filter","enabled":true,"visible":false,"color":"#8c927e","point_count":1,"filter":{"type":"county","key":"map_county","value":"DK:DK:DK:UNKNOWN:DK:DK:UNKNOWN:Unknown"}},{"id":"county:DZ:DZ:DZ:UNKNOWN:DZ:DZ:UNKNOWN:Unknown","label":"DZ:DZ:UNKNOWN:Unknown","kind":"county-filter","enabled":true,"visible":false,"color":"#8c927e","point_count":1,"filter":{"type":"county","key":"map_county","value":"DZ:DZ:DZ:UNKNOWN:DZ:DZ:UNKNOWN:Unknown"}},{"id":"county:EE:EE:EE:UNKNOWN:EE:EE:UNKNOWN:Unknown","label":"EE:EE:UNKNOWN:Unknown","kind":"county-filter","enabled":true,"visible":false,"color":"#8c927e","point_count":1,"filter":{"type":"county","key":"map_county","value":"EE:EE:EE:UNKNOWN:EE:EE:UNKNOWN:Unknown"}},{"id":"county:FO:FO:FO:UNKNOWN:FO:FO:UNKNOWN:Unknown","label":"FO:FO:UNKNOWN:Unknown","kind":"county-filter","enabled":true,"visible":false,"color":"#8c927e","point_count":1,"filter":{"type":"county","key":"map_county","value":"FO:FO:FO:UNKNOWN:FO:FO:UNKNOWN:Unknown"}},{"id":"county:HR:HR:HR:UNKNOWN:HR:HR:UNKNOWN:Unknown","label":"HR:HR:UNKNOWN:Unknown","kind":"county-filter","enabled":true,"visible":false,"color":"#8c927e","point_count":1,"filter":{"type":"county","key":"map_county","value":"HR:HR:HR:UNKNOWN:HR:HR:UNKNOWN:Unknown"}},{"id":"county:ID:ID:ID:UNKNOWN:ID:ID:UNKNOWN:Unknown","label":"ID:ID:UNKNOWN:Unknown","kind":"county-filter","enabled":true,"visible":false,"color":"#8c927e","point_count":1,"filter":{"type":"county","key":"map_county","value":"ID:ID:ID:UNKNOWN:ID:ID:UNKNOWN:Unknown"}},{"id":"county:IS:IS:IS:UNKNOWN:IS:IS:UNKNOWN:Unknown","label":"IS:IS:UNKNOWN:Unknown","kind":"county-filter","enabled":true,"visible":false,"color":"#8c927e","point_count":1,"filter":{"type":"county","key":"map_county","value":"IS:IS:IS:UNKNOWN:IS:IS:UNKNOWN:Unknown"}},{"id":"county:KW:KW:KW:UNKNOWN:KW:KW:UNKNOWN:Unknown","label":"KW:KW:UNKNOWN:Unknown","kind":"county-filter","enabled":true,"visible":false,"color":"#8c927e","point_count":1,"filter":{"type":"county","key":"map_county","value":"KW:KW:KW:UNKNOWN:KW:KW:UNKNOWN:Unknown"}},{"id":"county:KZ:KZ:KZ:UNKNOWN:KZ:KZ:UNKNOWN:Unknown","label":"KZ:KZ:UNKNOWN:Unknown","kind":"county-filter","enabled":true,"visible":false,"color":"#8c927e","point_count":1,"filter":{"type":"county","key":"map_county","value":"KZ:KZ:KZ:UNKNOWN:KZ:KZ:UNKNOWN:Unknown"}},{"id":"county:LI:LI:LI:UNKNOWN:LI:LI:UNKNOWN:Unknown","label":"LI:LI:UNKNOWN:Unknown","kind":"county-filter","enabled":true,"visible":false,"color":"#8c927e","point_count":1,"filter":{"type":"county","key":"map_county","value":"LI:LI:LI:UNKNOWN:LI:LI:UNKNOWN:Unknown"}},{"id":"county:LU:LU:LU:UNKNOWN:LU:LU:UNKNOWN:Unknown","label":"LU:LU:UNKNOWN:Unknown","kind":"county-filter","enabled":true,"visible":false,"color":"#8c927e","point_count":1,"filter":{"type":"county","key":"map_county","value":"LU:LU:LU:UNKNOWN:LU:LU:UNKNOWN:Unknown"}},{"id":"county:MD:MD:MD:UNKNOWN:MD:MD:UNKNOWN:Unknown","label":"MD:MD:UNKNOWN:Unknown","kind":"county-filter","enabled":true,"visible":false,"color":"#8c927e","point_count":1,"filter":{"type":"county","key":"map_county","value":"MD:MD:MD:UNKNOWN:MD:MD:UNKNOWN:Unknown"}},{"id":"county:MY:MY:MY:UNKNOWN:MY:MY:UNKNOWN:Unknown","label":"MY:MY:UNKNOWN:Unknown","kind":"county-filter","enabled":true,"visible":false,"color":"#8c927e","point_count":1,"filter":{"type":"county","key":"map_county","value":"MY:MY:MY:UNKNOWN:MY:MY:UNKNOWN:Unknown"}},{"id":"county:PR:PR:PR:UNKNOWN:PR:PR:UNKNOWN:Unknown","label":"PR:PR:UNKNOWN:Unknown","kind":"county-filter","enabled":true,"visible":false,"color":"#8c927e","point_count":1,"filter":{"type":"county","key":"map_county","value":"PR:PR:PR:UNKNOWN:PR:PR:UNKNOWN:Unknown"}},{"id":"county:RS:RS:RS:UNKNOWN:RS:RS:UNKNOWN:Unknown","label":"RS:RS:UNKNOWN:Unknown","kind":"county-filter","enabled":true,"visible":false,"color":"#8c927e","point_count":1,"filter":{"type":"county","key":"map_county","value":"RS:RS:RS:UNKNOWN:RS:RS:UNKNOWN:Unknown"}},{"id":"county:SA:SA:SA:UNKNOWN:SA:SA:UNKNOWN:Unknown","label":"SA:SA:UNKNOWN:Unknown","kind":"county-filter","enabled":true,"visible":false,"color":"#8c927e","point_count":1,"filter":{"type":"county","key":"map_county","value":"SA:SA:SA:UNKNOWN:SA:SA:UNKNOWN:Unknown"}},{"id":"county:VE:VE:VE:UNKNOWN:VE:VE:UNKNOWN:Unknown","label":"VE:VE:UNKNOWN:Unknown","kind":"county-filter","enabled":true,"visible":false,"color":"#8c927e","point_count":1,"filter":{"type":"county","key":"map_county","value":"VE:VE:VE:UNKNOWN:VE:VE:UNKNOWN:Unknown"}}]}
