{"name":"18.46","total_nodes":1,"reachable_nodes":1,"unreachable_nodes":0,"known_nodes":1,"tor_nodes":0,"i2p_nodes":0,"ipv4_nodes":1,"ipv6_nodes":0,"vpn_nodes":0,"proxy_nodes":0,"avg_latency_ms":18.51,"latest_height":951514,"top_agent":"/Satoshi:30.0.0/","top_asn":"AS12119","top_organization":"ITV-3","top_port":"8333","provider":"18.46","nodes":[{"rank":324,"address":"140.141.242.41:8333","host":"140.141.242.41","port":8333,"network":"ipv4","reachable":true,"protocol":70016,"agent":"/Satoshi:30.0.0/","connected_since":1780029824,"services":3145,"height":951514,"hostname":null,"city":"St. Peters Township","country":"US","latitude":38.725,"longitude":-90.5541,"timezone":null,"asn":"AS12119","organization":"ITV-3","provider":18.46,"county":null,"zip":null,"postal_code":null,"w3w":null,"what3words":null,"geohash":null,"geohashid":null,"asn_location":null,"latency_ms":18.51,"uptime_human":"14m","uptime_seconds":890.0,"peer_index":296.5452,"tor":false,"i2p":false,"is_tor":false,"is_i2p":false,"is_ipv4":true,"is_ipv6":false,"is_proxy":false,"is_vpn":false,"success_count":2,"failure_count":0,"first_seen":1780027905,"last_seen":1780028795,"metadata":{"latency_ms":18.51,"uptime_human":"14m","total_uptime":890.0,"reachable":true,"peer_index":296.5452,"tor":false,"i2p":false,"is_tor":false,"is_i2p":false,"is_ipv4":true,"is_ipv6":false,"is_vpn":false,"is_proxy":false,"success_count":2,"failure_count":0,"first_seen":1780027905,"first_seen_iso":"2026-05-29T04:11:45Z","last_seen":1780028795,"last_seen_iso":"2026-05-29T04:26:35Z","last_failure":null,"last_failure_iso":null,"network":"ipv4"}}]}
