{
  "updated_at": "2026-05-28T19:42:15.664259Z",
  "source": "coingecko_current_markets",
  "scope": "non_bitcoin_cryptoassets_currently_listed",
  "pages_scanned": 10,
  "per_page": 250,
  "non_bitcoin_assets_count": 1249,
  "alive_non_bitcoin_market_cap_usd": 1093794163136.0,
  "alive_non_bitcoin_volume_24h_usd": 136306385124.90175,
  "dead_or_inactive_market_cap_usd": null,
  "total_non_bitcoin_market_cap_usd": 1093794163136.0,
  "bitcoin_excluded": true,
  "top_non_bitcoin_assets": [
    {
      "rank": 2,
      "id": "ethereum",
      "symbol": "eth",
      "name": "Ethereum",
      "market_cap_usd": 243414665849.0,
      "volume_24h_usd": 18733314419.0,
      "price_usd": 2015.99,
      "price_change_24h_percent": -1.86426
    },
    {
      "rank": 3,
      "id": "tether",
      "symbol": "usdt",
      "name": "Tether",
      "market_cap_usd": 189296509606.0,
      "volume_24h_usd": 70340551233.0,
      "price_usd": 0.998483,
      "price_change_24h_percent": 0.02369
    },
    {
      "rank": 4,
      "id": "binancecoin",
      "symbol": "bnb",
      "name": "BNB",
      "market_cap_usd": 86217985036.0,
      "volume_24h_usd": 894700212.0,
      "price_usd": 639.52,
      "price_change_24h_percent": -1.98738
    },
    {
      "rank": 5,
      "id": "ripple",
      "symbol": "xrp",
      "name": "XRP",
      "market_cap_usd": 81765027493.0,
      "volume_24h_usd": 2453668830.0,
      "price_usd": 1.32,
      "price_change_24h_percent": -0.74513
    },
    {
      "rank": 6,
      "id": "usd-coin",
      "symbol": "usdc",
      "name": "USDC",
      "market_cap_usd": 76143640500.0,
      "volume_24h_usd": 15962748538.0,
      "price_usd": 0.999594,
      "price_change_24h_percent": -0.01188
    },
    {
      "rank": 7,
      "id": "solana",
      "symbol": "sol",
      "name": "Solana",
      "market_cap_usd": 47590948429.0,
      "volume_24h_usd": 3141078963.0,
      "price_usd": 82.28,
      "price_change_24h_percent": -1.89647
    },
    {
      "rank": 8,
      "id": "tron",
      "symbol": "trx",
      "name": "TRON",
      "market_cap_usd": 33415642449.0,
      "volume_24h_usd": 914038205.0,
      "price_usd": 0.352339,
      "price_change_24h_percent": -4.57646
    },
    {
      "rank": 9,
      "id": "figure-heloc",
      "symbol": "figr_heloc",
      "name": "Figure Heloc",
      "market_cap_usd": 18941155245.0,
      "volume_24h_usd": 54335631.0,
      "price_usd": 1.04,
      "price_change_24h_percent": 1.44893
    },
    {
      "rank": 10,
      "id": "dogecoin",
      "symbol": "doge",
      "name": "Dogecoin",
      "market_cap_usd": 15417747381.0,
      "volume_24h_usd": 945597627.0,
      "price_usd": 0.099787,
      "price_change_24h_percent": -2.11404
    },
    {
      "rank": 11,
      "id": "hyperliquid",
      "symbol": "hype",
      "name": "Hyperliquid",
      "market_cap_usd": 13467354715.0,
      "volume_24h_usd": 976207171.0,
      "price_usd": 60.51,
      "price_change_24h_percent": 1.38493
    },
    {
      "rank": 12,
      "id": "usds",
      "symbol": "usds",
      "name": "USDS",
      "market_cap_usd": 11109638015.0,
      "volume_24h_usd": 11800588.0,
      "price_usd": 0.999756,
      "price_change_24h_percent": 0.03505
    },
    {
      "rank": 13,
      "id": "leo-token",
      "symbol": "leo",
      "name": "LEO Token",
      "market_cap_usd": 9223180905.0,
      "volume_24h_usd": 505071.0,
      "price_usd": 10.02,
      "price_change_24h_percent": -0.20444
    },
    {
      "rank": 14,
      "id": "zcash",
      "symbol": "zec",
      "name": "Zcash",
      "market_cap_usd": 9209548619.0,
      "volume_24h_usd": 663672062.0,
      "price_usd": 551.87,
      "price_change_24h_percent": -0.15551
    },
    {
      "rank": 15,
      "id": "rain",
      "symbol": "rain",
      "name": "Rain",
      "market_cap_usd": 8911905558.0,
      "volume_24h_usd": 41757758.0,
      "price_usd": 0.0143072,
      "price_change_24h_percent": -2.72171
    },
    {
      "rank": 16,
      "id": "cardano",
      "symbol": "ada",
      "name": "Cardano",
      "market_cap_usd": 8697273281.0,
      "volume_24h_usd": 498017017.0,
      "price_usd": 0.234869,
      "price_change_24h_percent": -2.27068
    },
    {
      "rank": 17,
      "id": "stellar",
      "symbol": "xlm",
      "name": "Stellar",
      "market_cap_usd": 6871597135.0,
      "volume_24h_usd": 1760480901.0,
      "price_usd": 0.204161,
      "price_change_24h_percent": 25.10057
    },
    {
      "rank": 18,
      "id": "monero",
      "symbol": "xmr",
      "name": "Monero",
      "market_cap_usd": 6608330916.0,
      "volume_24h_usd": 159237688.0,
      "price_usd": 351.72,
      "price_change_24h_percent": -10.95035
    },
    {
      "rank": 19,
      "id": "chainlink",
      "symbol": "link",
      "name": "Chainlink",
      "market_cap_usd": 6552157969.0,
      "volume_24h_usd": 364611877.0,
      "price_usd": 9.0,
      "price_change_24h_percent": -3.25285
    },
    {
      "rank": 20,
      "id": "whitebit",
      "symbol": "wbt",
      "name": "WhiteBIT Coin",
      "market_cap_usd": 6386041202.0,
      "volume_24h_usd": 104752129.0,
      "price_usd": 53.96,
      "price_change_24h_percent": -2.03693
    },
    {
      "rank": 21,
      "id": "bitcoin-cash",
      "symbol": "bch",
      "name": "Bitcoin Cash",
      "market_cap_usd": 6034750323.0,
      "volume_24h_usd": 367101522.0,
      "price_usd": 301.15,
      "price_change_24h_percent": -12.18258
    },
    {
      "rank": 22,
      "id": "canton-network",
      "symbol": "cc",
      "name": "Canton",
      "market_cap_usd": 5957382270.0,
      "volume_24h_usd": 6083638.0,
      "price_usd": 0.154322,
      "price_change_24h_percent": -1.0022
    },
    {
      "rank": 23,
      "id": "the-open-network",
      "symbol": "ton",
      "name": "Toncoin",
      "market_cap_usd": 4781817454.0,
      "volume_24h_usd": 293747983.0,
      "price_usd": 1.77,
      "price_change_24h_percent": -7.17711
    },
    {
      "rank": 24,
      "id": "usd1-wlfi",
      "symbol": "usd1",
      "name": "USD1",
      "market_cap_usd": 4743926738.0,
      "volume_24h_usd": 1675479052.0,
      "price_usd": 0.998037,
      "price_change_24h_percent": -0.00073
    },
    {
      "rank": 25,
      "id": "ethena-usde",
      "symbol": "usde",
      "name": "Ethena USDe",
      "market_cap_usd": 4488598962.0,
      "volume_24h_usd": 71935859.0,
      "price_usd": 0.99879,
      "price_change_24h_percent": 0.01085
    },
    {
      "rank": 26,
      "id": "dai",
      "symbol": "dai",
      "name": "Dai",
      "market_cap_usd": 4370247396.0,
      "volume_24h_usd": 214234432.0,
      "price_usd": 0.999544,
      "price_change_24h_percent": 0.00494
    },
    {
      "rank": 27,
      "id": "litecoin",
      "symbol": "ltc",
      "name": "Litecoin",
      "market_cap_usd": 4000889147.0,
      "volume_24h_usd": 298429511.0,
      "price_usd": 51.82,
      "price_change_24h_percent": -1.05158
    },
    {
      "rank": 28,
      "id": "memecore",
      "symbol": "m",
      "name": "MemeCore",
      "market_cap_usd": 3867498795.0,
      "volume_24h_usd": 4310155.0,
      "price_usd": 2.96,
      "price_change_24h_percent": -2.55675
    },
    {
      "rank": 29,
      "id": "hedera-hashgraph",
      "symbol": "hbar",
      "name": "Hedera",
      "market_cap_usd": 3854095990.0,
      "volume_24h_usd": 230300580.0,
      "price_usd": 0.088847,
      "price_change_24h_percent": 3.62368
    },
    {
      "rank": 30,
      "id": "avalanche-2",
      "symbol": "avax",
      "name": "Avalanche",
      "market_cap_usd": 3849287153.0,
      "volume_24h_usd": 227077968.0,
      "price_usd": 8.91,
      "price_change_24h_percent": -2.82901
    },
    {
      "rank": 31,
      "id": "sui",
      "symbol": "sui",
      "name": "Sui",
      "market_cap_usd": 3724907112.0,
      "volume_24h_usd": 706810834.0,
      "price_usd": 0.929892,
      "price_change_24h_percent": -5.08501
    },
    {
      "rank": 32,
      "id": "shiba-inu",
      "symbol": "shib",
      "name": "Shiba Inu",
      "market_cap_usd": 3159513349.0,
      "volume_24h_usd": 171128586.0,
      "price_usd": 5.36e-06,
      "price_change_24h_percent": -2.30346
    },
    {
      "rank": 34,
      "id": "paypal-usd",
      "symbol": "pyusd",
      "name": "PayPal USD",
      "market_cap_usd": 3143144227.0,
      "volume_24h_usd": 83609514.0,
      "price_usd": 0.999894,
      "price_change_24h_percent": 0.01493
    },
    {
      "rank": 33,
      "id": "near",
      "symbol": "near",
      "name": "NEAR Protocol",
      "market_cap_usd": 3141331083.0,
      "volume_24h_usd": 729244766.0,
      "price_usd": 2.42,
      "price_change_24h_percent": -10.15036
    },
    {
      "rank": 35,
      "id": "crypto-com-chain",
      "symbol": "cro",
      "name": "Cronos",
      "market_cap_usd": 3017761691.0,
      "volume_24h_usd": 12027081.0,
      "price_usd": 0.067309,
      "price_change_24h_percent": 0.24174
    },
    {
      "rank": 36,
      "id": "hashnote-usyc",
      "symbol": "usyc",
      "name": "Circle USYC",
      "market_cap_usd": 2997097837.0,
      "volume_24h_usd": 225029.0,
      "price_usd": 1.13,
      "price_change_24h_percent": 0.00822
    },
    {
      "rank": 37,
      "id": "tether-gold",
      "symbol": "xaut",
      "name": "Tether Gold",
      "market_cap_usd": 2655843039.0,
      "volume_24h_usd": 278936666.0,
      "price_usd": 4479.89,
      "price_change_24h_percent": 0.84539
    },
    {
      "rank": 38,
      "id": "global-dollar",
      "symbol": "usdg",
      "name": "Global Dollar",
      "market_cap_usd": 2650417000.0,
      "volume_24h_usd": 204603681.0,
      "price_usd": 0.999679,
      "price_change_24h_percent": 0.00146
    },
    {
      "rank": 39,
      "id": "bittensor",
      "symbol": "tao",
      "name": "Bittensor",
      "market_cap_usd": 2520393613.0,
      "volume_24h_usd": 210895437.0,
      "price_usd": 262.3,
      "price_change_24h_percent": -4.0794
    },
    {
      "rank": 40,
      "id": "blackrock-usd-institutional-digital-liquidity-fund",
      "symbol": "buidl",
      "name": "BlackRock USD Institutional Digital Liquidity Fund",
      "market_cap_usd": 2455074843.0,
      "volume_24h_usd": 0.0,
      "price_usd": 1.0,
      "price_change_24h_percent": 0.0
    },
    {
      "rank": 41,
      "id": "ondo-us-dollar-yield",
      "symbol": "usdy",
      "name": "Ondo US Dollar Yield",
      "market_cap_usd": 2141062128.0,
      "volume_24h_usd": 122491.0,
      "price_usd": 1.13,
      "price_change_24h_percent": 0.04288
    },
    {
      "rank": 42,
      "id": "pax-gold",
      "symbol": "paxg",
      "name": "PAX Gold",
      "market_cap_usd": 2095472569.0,
      "volume_24h_usd": 256710960.0,
      "price_usd": 4486.38,
      "price_change_24h_percent": 0.80763
    },
    {
      "rank": 43,
      "id": "mantle",
      "symbol": "mnt",
      "name": "Mantle",
      "market_cap_usd": 2078409857.0,
      "volume_24h_usd": 64904859.0,
      "price_usd": 0.628953,
      "price_change_24h_percent": -1.05978
    },
    {
      "rank": 44,
      "id": "polkadot",
      "symbol": "dot",
      "name": "Polkadot",
      "market_cap_usd": 2060002326.0,
      "volume_24h_usd": 192248100.0,
      "price_usd": 1.22,
      "price_change_24h_percent": -2.99862
    },
    {
      "rank": 45,
      "id": "uniswap",
      "symbol": "uni",
      "name": "Uniswap",
      "market_cap_usd": 1942222636.0,
      "volume_24h_usd": 374737369.0,
      "price_usd": 3.06,
      "price_change_24h_percent": -6.50174
    },
    {
      "rank": 46,
      "id": "world-liberty-financial",
      "symbol": "wlfi",
      "name": "World Liberty Financial",
      "market_cap_usd": 1885450652.0,
      "volume_24h_usd": 50145892.0,
      "price_usd": 0.059292,
      "price_change_24h_percent": -0.7035
    },
    {
      "rank": 47,
      "id": "okb",
      "symbol": "okb",
      "name": "OKB",
      "market_cap_usd": 1831615000.0,
      "volume_24h_usd": 30436583.0,
      "price_usd": 87.2,
      "price_change_24h_percent": -0.62805
    },
    {
      "rank": 48,
      "id": "ondo-finance",
      "symbol": "ondo",
      "name": "Ondo",
      "market_cap_usd": 1806187114.0,
      "volume_24h_usd": 262639644.0,
      "price_usd": 0.37092,
      "price_change_24h_percent": -6.74146
    },
    {
      "rank": 49,
      "id": "aster-2",
      "symbol": "aster",
      "name": "Aster",
      "market_cap_usd": 1742579998.0,
      "volume_24h_usd": 83544848.0,
      "price_usd": 0.675103,
      "price_change_24h_percent": -1.54063
    },
    {
      "rank": 50,
      "id": "ripple-usd",
      "symbol": "rlusd",
      "name": "Ripple USD",
      "market_cap_usd": 1725104571.0,
      "volume_24h_usd": 262251595.0,
      "price_usd": 0.999715,
      "price_change_24h_percent": -0.06044
    },
    {
      "rank": 51,
      "id": "htx-dao",
      "symbol": "htx",
      "name": "HTX DAO",
      "market_cap_usd": 1683375902.0,
      "volume_24h_usd": 16482115.0,
      "price_usd": 1.86e-06,
      "price_change_24h_percent": -3.96397
    }
  ],
  "note": "This file measures currently listed non-Bitcoin cryptoasset market cap. Dead/inactive historical market cap requires a separate archival dataset. CoinGecko free market data does not provide reliable historical dead-coin loss accounting."
}
