{
  "source": "zzx-global-bpi",
  "mode": "generated",
  "base": "USD",
  "updated_at": "2026-07-20T08:07:44.157192Z",
  "mined_supply_btc": 20343750.0,
  "price_usd": 64222.97942780248,
  "btc_usd": 64222.97942780248,
  "vwap_usd": 64222.97942780248,
  "bpi_usd": 64222.97942780248,
  "volume_24h_btc": 32085.33464162764,
  "volume_24h_usd": 2066717301.9565327,
  "high_24h": 65088.59802107144,
  "low_24h": 63752.68330590182,
  "exchange_count": 14,
  "bpi_exchange_count": 13,
  "weighted_average": {
    "method": "supply_ratio_normalized_24h_exchange_volume_weighted_average",
    "sources": 13,
    "price_usd": 64222.97942780248,
    "vwap_usd": 64222.97942780248,
    "formula": "weight_i=(volume_24h_btc_i/mined_supply_btc)/sum(volume_24h_btc/mined_supply_btc); bpi=sum(price_i*weight_i)",
    "coingecko_policy": "CoinGecko global is selectable/displayable but excluded from ZZX BPI. CoinGecko exchange endpoints are allowed only as per-exchange fallback."
  },
  "global_bpi": {
    "price_usd": 64222.97942780248,
    "vwap_usd": 64222.97942780248
  },
  "exchanges": {
    "coinbase": {
      "label": "Coinbase",
      "source": "coinbase",
      "mode": "direct",
      "pair": "BTC-USD",
      "include_in_bpi": true,
      "price_usd": 64171.84,
      "volume_24h_btc": 4097.06650861,
      "volume_24h_usd": 262916296.45987952,
      "high_24h": 65050.87,
      "low_24h": 63702.01,
      "supply_ratio": 0.00020139190211293392,
      "updated_at": "2026-07-20T08:07:44.157192Z",
      "weight": 0.12769280901606833
    },
    "kraken": {
      "label": "Kraken",
      "source": "kraken",
      "mode": "direct",
      "pair": "XBT-USD",
      "include_in_bpi": true,
      "price_usd": 64180.3,
      "volume_24h_btc": 1025.22046025,
      "volume_24h_usd": 65798956.704983085,
      "high_24h": 65045.2,
      "low_24h": 63691.6,
      "supply_ratio": 5.039486133333334e-05,
      "updated_at": "2026-07-20T08:07:44.157192Z",
      "weight": 0.03195293026240951
    },
    "gemini": {
      "label": "Gemini",
      "source": "gemini",
      "mode": "direct",
      "pair": "BTC-USD",
      "include_in_bpi": true,
      "price_usd": 64180.81,
      "volume_24h_btc": 90.63216868,
      "volume_24h_usd": 5816845.997939031,
      "high_24h": 64180.81,
      "low_24h": 64180.81,
      "supply_ratio": 4.455037477357911e-06,
      "updated_at": "2026-07-20T08:07:44.157192Z",
      "weight": 0.002824722562264115
    },
    "bitstamp": {
      "label": "Bitstamp",
      "source": "bitstamp",
      "mode": "direct",
      "pair": "BTC-USD",
      "include_in_bpi": true,
      "price_usd": 64177.46,
      "volume_24h_btc": 751.29130638,
      "volume_24h_usd": 48215967.7635502,
      "high_24h": 65047.24,
      "low_24h": 63705.77,
      "supply_ratio": 3.6929833800553e-05,
      "updated_at": "2026-07-20T08:07:44.157192Z",
      "weight": 0.023415411270333822
    },
    "bitfinex": {
      "label": "Bitfinex",
      "source": "bitfinex",
      "mode": "direct",
      "pair": "BTC-USD",
      "include_in_bpi": true,
      "price_usd": 64266.0,
      "volume_24h_btc": 459.5521054,
      "volume_24h_usd": 29533575.6056364,
      "high_24h": 65148.0,
      "low_24h": 63800.0,
      "supply_ratio": 2.25893508030722e-05,
      "updated_at": "2026-07-20T08:07:44.157192Z",
      "weight": 0.014322808552034714
    },
    "okx": {
      "label": "OKX",
      "source": "okx",
      "mode": "direct",
      "pair": "BTC-USDT",
      "include_in_bpi": true,
      "price_usd": 64234.5,
      "volume_24h_btc": 7606.07130907,
      "volume_24h_usd": 490498624.48013175,
      "high_24h": 65111.1,
      "low_24h": 63762.4,
      "supply_ratio": 0.000373877545146298,
      "updated_at": "2026-07-20T08:07:44.157192Z",
      "weight": 0.23705756520930446
    },
    "crypto_com": {
      "label": "Crypto.com",
      "source": "crypto_com",
      "mode": "direct",
      "pair": "BTC-USD",
      "include_in_bpi": true,
      "price_usd": 64181.98,
      "volume_24h_btc": 2147.151,
      "volume_24h_usd": 137808402.53898,
      "high_24h": 65064.49,
      "low_24h": 63712.32,
      "supply_ratio": 0.00010554352073732718,
      "updated_at": "2026-07-20T08:07:44.157192Z",
      "weight": 0.06692001264697042
    },
    "kucoin": {
      "label": "KuCoin",
      "source": "kucoin",
      "mode": "direct",
      "pair": "BTC-USDT",
      "include_in_bpi": true,
      "price_usd": 64236.0,
      "volume_24h_btc": 2053.13248388,
      "volume_24h_usd": 132415964.4733701,
      "high_24h": 65099.9,
      "low_24h": 63766.4,
      "supply_ratio": 0.00010092202685738863,
      "updated_at": "2026-07-20T08:07:44.157192Z",
      "weight": 0.06398974817660956
    },
    "gateio": {
      "label": "Gate.io",
      "source": "gateio",
      "mode": "direct",
      "pair": "BTC-USDT",
      "include_in_bpi": true,
      "price_usd": 64236.6,
      "volume_24h_btc": 4969.796712,
      "volume_24h_usd": 320485166.1034361,
      "high_24h": 65106.6,
      "low_24h": 63769.4,
      "supply_ratio": 0.0002442910826175115,
      "updated_at": "2026-07-20T08:07:44.157192Z",
      "weight": 0.15489309267019974
    },
    "bitget": {
      "label": "Bitget",
      "source": "bitget",
      "mode": "direct",
      "pair": "BTC-USDT",
      "include_in_bpi": true,
      "price_usd": 64234.89,
      "volume_24h_btc": 1355.665768,
      "volume_24h_usd": 87369221.312112,
      "high_24h": 65109.16,
      "low_24h": 63764.01,
      "supply_ratio": 6.663794865745009e-05,
      "updated_at": "2026-07-20T08:07:44.157192Z",
      "weight": 0.042251881837665296
    },
    "mexc": {
      "label": "MEXC",
      "source": "mexc",
      "mode": "direct",
      "pair": "BTC-USDT",
      "include_in_bpi": true,
      "price_usd": 64244.56,
      "volume_24h_btc": 5851.63939865,
      "volume_24h_usd": 377495985.02,
      "high_24h": 65100.0,
      "low_24h": 63770.49,
      "supply_ratio": 0.00028763818856651304,
      "updated_at": "2026-07-20T08:07:44.157192Z",
      "weight": 0.18237738406063123
    },
    "htx": {
      "label": "HTX",
      "source": "htx",
      "mode": "direct",
      "pair": "BTC-USDT",
      "include_in_bpi": true,
      "price_usd": 64244.23,
      "volume_24h_btc": 1667.3688307076416,
      "volume_24h_usd": 107669857.73878947,
      "high_24h": 65063.95,
      "low_24h": 63769.06,
      "supply_ratio": 8.195975819146625e-05,
      "updated_at": "2026-07-20T08:07:44.157192Z",
      "weight": 0.05196669597905302
    },
    "okcoin": {
      "label": "OKCoin",
      "source": "okcoin",
      "include_in_bpi": true,
      "error": "HTTP Error 404: Not Found",
      "updated_at": "2026-07-20T08:07:44.157192Z"
    },
    "binance_us": {
      "label": "Binance US",
      "source": "binance_us",
      "mode": "direct",
      "pair": "BTC-USD",
      "include_in_bpi": true,
      "price_usd": 64190.2,
      "volume_24h_btc": 10.74659,
      "volume_24h_usd": 692437.757725,
      "high_24h": 65047.5,
      "low_24h": 63714.97,
      "supply_ratio": 5.282501996927803e-07,
      "updated_at": "2026-07-20T08:07:44.157192Z",
      "weight": 0.00033493775645578993
    },
    "coingecko_global": {
      "label": "CoinGecko Global",
      "source": "coingecko_global",
      "mode": "direct",
      "pair": "BTC-global",
      "include_in_bpi": false,
      "price_usd": 64205.32697015069,
      "volume_24h_btc": 146109.10830438192,
      "volume_24h_usd": 9380983072.0,
      "high_24h": 64302.0,
      "low_24h": 63849.0,
      "supply_ratio": 0.0071820145403075596,
      "updated_at": "2026-07-20T08:07:44.157192Z"
    }
  }
}
