{"name":"Yongsan-dong (Hangang-daero), KR","total_nodes":12,"reachable_nodes":12,"reachable_now":0,"reachable_24h":0,"unreachable_nodes":0,"known_nodes":12,"tor_nodes":0,"i2p_nodes":0,"ipv4_nodes":12,"ipv6_nodes":0,"vpn_nodes":0,"proxy_nodes":0,"sanctioned_nodes":0,"policy_restricted_nodes":0,"avg_latency_ms":387.1058,"latest_height":951806,"top_agent":"/Satoshi:30.0.0/","top_asn":"AS17858","top_organization":"LG POWERCOMM","top_port":"8333","city":"Yongsan-dong (Hangang-daero)","country":"KR","nodes":[{"rank":840,"address":"110.45.178.102:8333","host":"110.45.178.102","port":8333,"network":"ipv4","protocol":70016,"protocol_version":70016,"agent":"/Satoshi:31.0.0/","user_agent":"/Satoshi:31.0.0/","connected_since":1780206366,"services":3081,"height":951806,"hostname":null,"city":"Yongsan-dong (Hangang-daero)","country":"KR","country_code":"KR","latitude":37.5379,"longitude":126.97,"timezone":null,"asn":"AS3786","organization":"LG DACOM Corporation","provider":374.84,"county":null,"zip":null,"postal_code":null,"w3w":null,"what3words":null,"geohash":null,"geohashid":null,"asn_location":null,"latency_ms":374.91,"uptime_human":"3d","uptime_seconds":285948.0,"total_uptime":285948.0,"daily_latency_ms":null,"weekly_latency_ms":null,"monthly_latency_ms":null,"daily_uptime_seconds":null,"weekly_uptime_seconds":null,"monthly_uptime_seconds":null,"peer_index":304.448,"peer_health":null,"reachable_now":null,"reachable_24h":null,"tor":false,"i2p":false,"is_tor":false,"is_i2p":false,"is_ipv4":true,"is_ipv6":false,"is_proxy":false,"is_vpn":false,"is_sanctioned_node":false,"is_policy_restricted_node":false,"jurisdiction_risk_level":null,"continent":null,"region":null,"territory":null,"success_count":287,"failure_count":0,"first_seen":1779920377,"last_seen":1780206325,"last_failure":null,"metadata":{"latency_ms":374.91,"uptime_human":"3d","total_uptime":285948.0,"reachable":true,"peer_index":304.448,"tor":false,"i2p":false,"is_tor":false,"is_i2p":false,"is_ipv4":true,"is_ipv6":false,"is_vpn":false,"is_proxy":false,"success_count":287,"failure_count":0,"first_seen":1779920377,"first_seen_iso":"2026-05-27T22:19:37Z","last_seen":1780206325,"last_seen_iso":"2026-05-31T05:45:25Z","last_failure":null,"last_failure_iso":null,"network":"ipv4"},"reachable":true},{"rank":866,"address":"122.32.38.191:8333","host":"122.32.38.191","port":8333,"network":"ipv4","protocol":70016,"protocol_version":70016,"agent":"/Satoshi:30.2.0/","user_agent":"/Satoshi:30.2.0/","connected_since":1780206371,"services":3145,"height":951806,"hostname":null,"city":"Yongsan-dong (Hangang-daero)","country":"KR","country_code":"KR","latitude":37.5379,"longitude":126.97,"timezone":null,"asn":"AS17858","organization":"LG POWERCOMM","provider":392.24,"county":null,"zip":null,"postal_code":null,"w3w":null,"what3words":null,"geohash":null,"geohashid":null,"asn_location":null,"latency_ms":392.29,"uptime_human":"3d","uptime_seconds":287999.0,"total_uptime":287999.0,"daily_latency_ms":null,"weekly_latency_ms":null,"monthly_latency_ms":null,"daily_uptime_seconds":null,"weekly_uptime_seconds":null,"monthly_uptime_seconds":null,"peer_index":301.5417,"peer_health":null,"reachable_now":null,"reachable_24h":null,"tor":false,"i2p":false,"is_tor":false,"is_i2p":false,"is_ipv4":true,"is_ipv6":false,"is_proxy":false,"is_vpn":false,"is_sanctioned_node":false,"is_policy_restricted_node":false,"jurisdiction_risk_level":null,"continent":null,"region":null,"territory":null,"success_count":296,"failure_count":0,"first_seen":1779918326,"last_seen":1780206325,"last_failure":null,"metadata":{"latency_ms":392.29,"uptime_human":"3d","total_uptime":287999.0,"reachable":true,"peer_index":301.5417,"tor":false,"i2p":false,"is_tor":false,"is_i2p":false,"is_ipv4":true,"is_ipv6":false,"is_vpn":false,"is_proxy":false,"success_count":296,"failure_count":0,"first_seen":1779918326,"first_seen_iso":"2026-05-27T21:45:26Z","last_seen":1780206325,"last_seen_iso":"2026-05-31T05:45:25Z","last_failure":null,"last_failure_iso":null,"network":"ipv4"},"reachable":true},{"rank":884,"address":"125.181.201.95:8333","host":"125.181.201.95","port":8333,"network":"ipv4","protocol":70016,"protocol_version":70016,"agent":"/Satoshi:30.0.0/","user_agent":"/Satoshi:30.0.0/","connected_since":1780206371,"services":3145,"height":951806,"hostname":null,"city":"Yongsan-dong (Hangang-daero)","country":"KR","country_code":"KR","latitude":37.5379,"longitude":126.97,"timezone":null,"asn":"AS17858","organization":"LG POWERCOMM","provider":394.12,"county":null,"zip":null,"postal_code":null,"w3w":null,"what3words":null,"geohash":null,"geohashid":null,"asn_location":null,"latency_ms":394.16,"uptime_human":"3d","uptime_seconds":277926.0,"total_uptime":277926.0,"daily_latency_ms":null,"weekly_latency_ms":null,"monthly_latency_ms":null,"daily_uptime_seconds":null,"weekly_uptime_seconds":null,"monthly_uptime_seconds":null,"peer_index":298.3697,"peer_health":null,"reachable_now":null,"reachable_24h":null,"tor":false,"i2p":false,"is_tor":false,"is_i2p":false,"is_ipv4":true,"is_ipv6":false,"is_proxy":false,"is_vpn":false,"is_sanctioned_node":false,"is_policy_restricted_node":false,"jurisdiction_risk_level":null,"continent":null,"region":null,"territory":null,"success_count":236,"failure_count":0,"first_seen":1779928399,"last_seen":1780206325,"last_failure":null,"metadata":{"latency_ms":394.16,"uptime_human":"3d","total_uptime":277926.0,"reachable":true,"peer_index":298.3697,"tor":false,"i2p":false,"is_tor":false,"is_i2p":false,"is_ipv4":true,"is_ipv6":false,"is_vpn":false,"is_proxy":false,"success_count":236,"failure_count":0,"first_seen":1779928399,"first_seen_iso":"2026-05-28T00:33:19Z","last_seen":1780206325,"last_seen_iso":"2026-05-31T05:45:25Z","last_failure":null,"last_failure_iso":null,"network":"ipv4"},"reachable":true},{"rank":919,"address":"124.52.100.157:8333","host":"124.52.100.157","port":8333,"network":"ipv4","protocol":70016,"protocol_version":70016,"agent":"/Satoshi:29.0.0/","user_agent":"/Satoshi:29.0.0/","connected_since":1780206371,"services":3081,"height":951806,"hostname":null,"city":"Yongsan-dong (Hangang-daero)","country":"KR","country_code":"KR","latitude":37.5379,"longitude":126.97,"timezone":null,"asn":"AS17858","organization":"LG POWERCOMM","provider":397.8,"county":null,"zip":null,"postal_code":null,"w3w":null,"what3words":null,"geohash":null,"geohashid":null,"asn_location":null,"latency_ms":397.84,"uptime_human":"3d","uptime_seconds":264443.0,"total_uptime":264443.0,"daily_latency_ms":null,"weekly_latency_ms":null,"monthly_latency_ms":null,"daily_uptime_seconds":null,"weekly_uptime_seconds":null,"monthly_uptime_seconds":null,"peer_index":291.9372,"peer_health":null,"reachable_now":null,"reachable_24h":null,"tor":false,"i2p":false,"is_tor":false,"is_i2p":false,"is_ipv4":true,"is_ipv6":false,"is_proxy":false,"is_vpn":false,"is_sanctioned_node":false,"is_policy_restricted_node":false,"jurisdiction_risk_level":null,"continent":null,"region":null,"territory":null,"success_count":201,"failure_count":4,"first_seen":1779941075,"last_seen":1780206325,"last_failure":null,"metadata":{"latency_ms":397.84,"uptime_human":"3d","total_uptime":264443.0,"reachable":true,"peer_index":291.9372,"tor":false,"i2p":false,"is_tor":false,"is_i2p":false,"is_ipv4":true,"is_ipv6":false,"is_vpn":false,"is_proxy":false,"success_count":201,"failure_count":4,"first_seen":1779941075,"first_seen_iso":"2026-05-28T04:04:35Z","last_seen":1780206325,"last_seen_iso":"2026-05-31T05:45:25Z","last_failure":null,"last_failure_iso":null,"network":"ipv4"},"reachable":true},{"rank":923,"address":"122.43.32.168:8333","host":"122.43.32.168","port":8333,"network":"ipv4","protocol":70016,"protocol_version":70016,"agent":"/Satoshi:30.0.0/","user_agent":"/Satoshi:30.0.0/","connected_since":1780206371,"services":3145,"height":951806,"hostname":null,"city":"Yongsan-dong (Hangang-daero)","country":"KR","country_code":"KR","latitude":37.5379,"longitude":126.97,"timezone":null,"asn":"AS17858","organization":"LG POWERCOMM","provider":405.65,"county":null,"zip":null,"postal_code":null,"w3w":null,"what3words":null,"geohash":null,"geohashid":null,"asn_location":null,"latency_ms":405.73,"uptime_human":"3d","uptime_seconds":259914.0,"total_uptime":259914.0,"daily_latency_ms":null,"weekly_latency_ms":null,"monthly_latency_ms":null,"daily_uptime_seconds":null,"weekly_uptime_seconds":null,"monthly_uptime_seconds":null,"peer_index":291.0523,"peer_health":null,"reachable_now":null,"reachable_24h":null,"tor":false,"i2p":false,"is_tor":false,"is_i2p":false,"is_ipv4":true,"is_ipv6":false,"is_proxy":false,"is_vpn":false,"is_sanctioned_node":false,"is_policy_restricted_node":false,"jurisdiction_risk_level":null,"continent":null,"region":null,"territory":null,"success_count":157,"failure_count":0,"first_seen":1779946411,"last_seen":1780206325,"last_failure":null,"metadata":{"latency_ms":405.73,"uptime_human":"3d","total_uptime":259914.0,"reachable":true,"peer_index":291.0523,"tor":false,"i2p":false,"is_tor":false,"is_i2p":false,"is_ipv4":true,"is_ipv6":false,"is_vpn":false,"is_proxy":false,"success_count":157,"failure_count":0,"first_seen":1779946411,"first_seen_iso":"2026-05-28T05:33:31Z","last_seen":1780206325,"last_seen_iso":"2026-05-31T05:45:25Z","last_failure":null,"last_failure_iso":null,"network":"ipv4"},"reachable":true},{"rank":970,"address":"116.41.254.226:8333","host":"116.41.254.226","port":8333,"network":"ipv4","protocol":70016,"protocol_version":70016,"agent":"/Satoshi:28.1.0(FutureBit-Apollo-Node)/","user_agent":"/Satoshi:28.1.0(FutureBit-Apollo-Node)/","connected_since":1780206366,"services":3081,"height":951806,"hostname":null,"city":"Yongsan-dong (Hangang-daero)","country":"KR","country_code":"KR","latitude":37.5379,"longitude":126.97,"timezone":null,"asn":"AS17858","organization":"LG POWERCOMM","provider":389.9,"county":null,"zip":null,"postal_code":null,"w3w":null,"what3words":null,"geohash":null,"geohashid":null,"asn_location":null,"latency_ms":390.09,"uptime_human":"2d","uptime_seconds":213300.0,"total_uptime":213300.0,"daily_latency_ms":null,"weekly_latency_ms":null,"monthly_latency_ms":null,"daily_uptime_seconds":null,"weekly_uptime_seconds":null,"monthly_uptime_seconds":null,"peer_index":281.232,"peer_health":null,"reachable_now":null,"reachable_24h":null,"tor":false,"i2p":false,"is_tor":false,"is_i2p":false,"is_ipv4":true,"is_ipv6":false,"is_proxy":false,"is_vpn":false,"is_sanctioned_node":false,"is_policy_restricted_node":false,"jurisdiction_risk_level":null,"continent":null,"region":null,"territory":null,"success_count":92,"failure_count":0,"first_seen":1779993025,"last_seen":1780206325,"last_failure":null,"metadata":{"latency_ms":390.09,"uptime_human":"2d","total_uptime":213300.0,"reachable":true,"peer_index":281.232,"tor":false,"i2p":false,"is_tor":false,"is_i2p":false,"is_ipv4":true,"is_ipv6":false,"is_vpn":false,"is_proxy":false,"success_count":92,"failure_count":0,"first_seen":1779993025,"first_seen_iso":"2026-05-28T18:30:25Z","last_seen":1780206325,"last_seen_iso":"2026-05-31T05:45:25Z","last_failure":null,"last_failure_iso":null,"network":"ipv4"},"reachable":true},{"rank":1004,"address":"117.52.250.5:20090","host":"117.52.250.5","port":20090,"network":"ipv4","protocol":70016,"protocol_version":70016,"agent":"/Satoshi:30.0.0/","user_agent":"/Satoshi:30.0.0/","connected_since":1780206371,"services":3081,"height":951806,"hostname":null,"city":"Yongsan-dong (Hangang-daero)","country":"KR","country_code":"KR","latitude":37.5379,"longitude":126.97,"timezone":null,"asn":"AS3786","organization":"LG DACOM Corporation","provider":370.23,"county":null,"zip":null,"postal_code":null,"w3w":null,"what3words":null,"geohash":null,"geohashid":null,"asn_location":null,"latency_ms":370.38,"uptime_human":"2d","uptime_seconds":178420.0,"total_uptime":178420.0,"daily_latency_ms":null,"weekly_latency_ms":null,"monthly_latency_ms":null,"daily_uptime_seconds":null,"weekly_uptime_seconds":null,"monthly_uptime_seconds":null,"peer_index":275.4851,"peer_health":null,"reachable_now":null,"reachable_24h":null,"tor":false,"i2p":false,"is_tor":false,"is_i2p":false,"is_ipv4":true,"is_ipv6":false,"is_proxy":false,"is_vpn":false,"is_sanctioned_node":false,"is_policy_restricted_node":false,"jurisdiction_risk_level":null,"continent":null,"region":null,"territory":null,"success_count":24,"failure_count":0,"first_seen":1780027905,"last_seen":1780206325,"last_failure":null,"metadata":{"latency_ms":370.38,"uptime_human":"2d","total_uptime":178420.0,"reachable":true,"peer_index":275.4851,"tor":false,"i2p":false,"is_tor":false,"is_i2p":false,"is_ipv4":true,"is_ipv6":false,"is_vpn":false,"is_proxy":false,"success_count":24,"failure_count":0,"first_seen":1780027905,"first_seen_iso":"2026-05-29T04:11:45Z","last_seen":1780206325,"last_seen_iso":"2026-05-31T05:45:25Z","last_failure":null,"last_failure_iso":null,"network":"ipv4"},"reachable":true},{"rank":1005,"address":"117.52.250.4:20090","host":"117.52.250.4","port":20090,"network":"ipv4","protocol":70016,"protocol_version":70016,"agent":"/Satoshi:30.0.0/","user_agent":"/Satoshi:30.0.0/","connected_since":1780206371,"services":3081,"height":951806,"hostname":null,"city":"Yongsan-dong (Hangang-daero)","country":"KR","country_code":"KR","latitude":37.5379,"longitude":126.97,"timezone":null,"asn":"AS3786","organization":"LG DACOM Corporation","provider":371.38,"county":null,"zip":null,"postal_code":null,"w3w":null,"what3words":null,"geohash":null,"geohashid":null,"asn_location":null,"latency_ms":371.44,"uptime_human":"2d","uptime_seconds":177530.0,"total_uptime":177530.0,"daily_latency_ms":null,"weekly_latency_ms":null,"monthly_latency_ms":null,"daily_uptime_seconds":null,"weekly_uptime_seconds":null,"monthly_uptime_seconds":null,"peer_index":275.0259,"peer_health":null,"reachable_now":null,"reachable_24h":null,"tor":false,"i2p":false,"is_tor":false,"is_i2p":false,"is_ipv4":true,"is_ipv6":false,"is_proxy":false,"is_vpn":false,"is_sanctioned_node":false,"is_policy_restricted_node":false,"jurisdiction_risk_level":null,"continent":null,"region":null,"territory":null,"success_count":23,"failure_count":0,"first_seen":1780028795,"last_seen":1780206325,"last_failure":null,"metadata":{"latency_ms":371.44,"uptime_human":"2d","total_uptime":177530.0,"reachable":true,"peer_index":275.0259,"tor":false,"i2p":false,"is_tor":false,"is_i2p":false,"is_ipv4":true,"is_ipv6":false,"is_vpn":false,"is_proxy":false,"success_count":23,"failure_count":0,"first_seen":1780028795,"first_seen_iso":"2026-05-29T04:26:35Z","last_seen":1780206325,"last_seen_iso":"2026-05-31T05:45:25Z","last_failure":null,"last_failure_iso":null,"network":"ipv4"},"reachable":true},{"rank":1013,"address":"112.157.154.16:9333","host":"112.157.154.16","port":9333,"network":"ipv4","protocol":70016,"protocol_version":70016,"agent":"/Satoshi:29.3.0/Knots:20260508/","user_agent":"/Satoshi:29.3.0/Knots:20260508/","connected_since":1780206366,"services":134220873,"height":951806,"hostname":null,"city":"Yongsan-dong (Hangang-daero)","country":"KR","country_code":"KR","latitude":37.5379,"longitude":126.97,"timezone":null,"asn":"AS17858","organization":"LG POWERCOMM","provider":380.31,"county":null,"zip":null,"postal_code":null,"w3w":null,"what3words":null,"geohash":null,"geohashid":null,"asn_location":null,"latency_ms":380.36,"uptime_human":"2d","uptime_seconds":178420.0,"total_uptime":178420.0,"daily_latency_ms":null,"weekly_latency_ms":null,"monthly_latency_ms":null,"daily_uptime_seconds":null,"weekly_uptime_seconds":null,"monthly_uptime_seconds":null,"peer_index":273.4891,"peer_health":null,"reachable_now":null,"reachable_24h":null,"tor":false,"i2p":false,"is_tor":false,"is_i2p":false,"is_ipv4":true,"is_ipv6":false,"is_proxy":false,"is_vpn":false,"is_sanctioned_node":false,"is_policy_restricted_node":false,"jurisdiction_risk_level":null,"continent":null,"region":null,"territory":null,"success_count":24,"failure_count":0,"first_seen":1780027905,"last_seen":1780206325,"last_failure":null,"metadata":{"latency_ms":380.36,"uptime_human":"2d","total_uptime":178420.0,"reachable":true,"peer_index":273.4891,"tor":false,"i2p":false,"is_tor":false,"is_i2p":false,"is_ipv4":true,"is_ipv6":false,"is_vpn":false,"is_proxy":false,"success_count":24,"failure_count":0,"first_seen":1780027905,"first_seen_iso":"2026-05-29T04:11:45Z","last_seen":1780206325,"last_seen_iso":"2026-05-31T05:45:25Z","last_failure":null,"last_failure_iso":null,"network":"ipv4"},"reachable":true},{"rank":1015,"address":"115.94.114.222:8333","host":"115.94.114.222","port":8333,"network":"ipv4","protocol":70016,"protocol_version":70016,"agent":"/Satoshi:22.0.0/","user_agent":"/Satoshi:22.0.0/","connected_since":1780206366,"services":1032,"height":951806,"hostname":null,"city":"Yongsan-dong (Hangang-daero)","country":"KR","country_code":"KR","latitude":37.5379,"longitude":126.97,"timezone":null,"asn":"AS3786","organization":"LG DACOM Corporation","provider":380.57,"county":null,"zip":null,"postal_code":null,"w3w":null,"what3words":null,"geohash":null,"geohashid":null,"asn_location":null,"latency_ms":380.63,"uptime_human":"2d","uptime_seconds":178420.0,"total_uptime":178420.0,"daily_latency_ms":null,"weekly_latency_ms":null,"monthly_latency_ms":null,"daily_uptime_seconds":null,"weekly_uptime_seconds":null,"monthly_uptime_seconds":null,"peer_index":273.4351,"peer_health":null,"reachable_now":null,"reachable_24h":null,"tor":false,"i2p":false,"is_tor":false,"is_i2p":false,"is_ipv4":true,"is_ipv6":false,"is_proxy":false,"is_vpn":false,"is_sanctioned_node":false,"is_policy_restricted_node":false,"jurisdiction_risk_level":null,"continent":null,"region":null,"territory":null,"success_count":24,"failure_count":0,"first_seen":1780027905,"last_seen":1780206325,"last_failure":null,"metadata":{"latency_ms":380.63,"uptime_human":"2d","total_uptime":178420.0,"reachable":true,"peer_index":273.4351,"tor":false,"i2p":false,"is_tor":false,"is_i2p":false,"is_ipv4":true,"is_ipv6":false,"is_vpn":false,"is_proxy":false,"success_count":24,"failure_count":0,"first_seen":1780027905,"first_seen_iso":"2026-05-29T04:11:45Z","last_seen":1780206325,"last_seen_iso":"2026-05-31T05:45:25Z","last_failure":null,"last_failure_iso":null,"network":"ipv4"},"reachable":true},{"rank":1030,"address":"14.6.201.26:8333","host":"14.6.201.26","port":8333,"network":"ipv4","protocol":70016,"protocol_version":70016,"agent":"/Satoshi:31.0.0/","user_agent":"/Satoshi:31.0.0/","connected_since":1780206381,"services":3145,"height":951806,"hostname":null,"city":"Yongsan-dong (Hangang-daero)","country":"KR","country_code":"KR","latitude":37.5379,"longitude":126.97,"timezone":null,"asn":"AS17858","organization":"LG POWERCOMM","provider":387.88,"county":null,"zip":null,"postal_code":null,"w3w":null,"what3words":null,"geohash":null,"geohashid":null,"asn_location":null,"latency_ms":387.94,"uptime_human":"2d","uptime_seconds":177530.0,"total_uptime":177530.0,"daily_latency_ms":null,"weekly_latency_ms":null,"monthly_latency_ms":null,"daily_uptime_seconds":null,"weekly_uptime_seconds":null,"monthly_uptime_seconds":null,"peer_index":271.7259,"peer_health":null,"reachable_now":null,"reachable_24h":null,"tor":false,"i2p":false,"is_tor":false,"is_i2p":false,"is_ipv4":true,"is_ipv6":false,"is_proxy":false,"is_vpn":false,"is_sanctioned_node":false,"is_policy_restricted_node":false,"jurisdiction_risk_level":null,"continent":null,"region":null,"territory":null,"success_count":23,"failure_count":0,"first_seen":1780028795,"last_seen":1780206325,"last_failure":null,"metadata":{"latency_ms":387.94,"uptime_human":"2d","total_uptime":177530.0,"reachable":true,"peer_index":271.7259,"tor":false,"i2p":false,"is_tor":false,"is_i2p":false,"is_ipv4":true,"is_ipv6":false,"is_vpn":false,"is_proxy":false,"success_count":23,"failure_count":0,"first_seen":1780028795,"first_seen_iso":"2026-05-29T04:26:35Z","last_seen":1780206325,"last_seen_iso":"2026-05-31T05:45:25Z","last_failure":null,"last_failure_iso":null,"network":"ipv4"},"reachable":true},{"rank":1044,"address":"116.32.185.104:8333","host":"116.32.185.104","port":8333,"network":"ipv4","protocol":70016,"protocol_version":70016,"agent":"/Satoshi:31.0.0/","user_agent":"/Satoshi:31.0.0/","connected_since":1780206366,"services":3145,"height":951806,"hostname":null,"city":"Yongsan-dong (Hangang-daero)","country":"KR","country_code":"KR","latitude":37.5379,"longitude":126.97,"timezone":null,"asn":"AS17858","organization":"LG POWERCOMM","provider":399.44,"county":null,"zip":null,"postal_code":null,"w3w":null,"what3words":null,"geohash":null,"geohashid":null,"asn_location":null,"latency_ms":399.5,"uptime_human":"2d","uptime_seconds":178420.0,"total_uptime":178420.0,"daily_latency_ms":null,"weekly_latency_ms":null,"monthly_latency_ms":null,"daily_uptime_seconds":null,"weekly_uptime_seconds":null,"monthly_uptime_seconds":null,"peer_index":269.6611,"peer_health":null,"reachable_now":null,"reachable_24h":null,"tor":false,"i2p":false,"is_tor":false,"is_i2p":false,"is_ipv4":true,"is_ipv6":false,"is_proxy":false,"is_vpn":false,"is_sanctioned_node":false,"is_policy_restricted_node":false,"jurisdiction_risk_level":null,"continent":null,"region":null,"territory":null,"success_count":24,"failure_count":0,"first_seen":1780027905,"last_seen":1780206325,"last_failure":null,"metadata":{"latency_ms":399.5,"uptime_human":"2d","total_uptime":178420.0,"reachable":true,"peer_index":269.6611,"tor":false,"i2p":false,"is_tor":false,"is_i2p":false,"is_ipv4":true,"is_ipv6":false,"is_vpn":false,"is_proxy":false,"success_count":24,"failure_count":0,"first_seen":1780027905,"first_seen_iso":"2026-05-29T04:11:45Z","last_seen":1780206325,"last_seen_iso":"2026-05-31T05:45:25Z","last_failure":null,"last_failure_iso":null,"network":"ipv4"},"reachable":true}]}
